domed/__init__.py
domed/core.py
domed/html.py
domed/svg.py
domed-0.2.0.dist-info/LICENSE
domed-0.2.0.dist-info/WHEEL
domed-0.2.0.dist-info/METADATA
domed-0.2.0.dist-info/RECORD
