Metadata-Version: 2.1
Name: domed
Version: 0.2.0
Summary: The `domed` package contains functionality for directly manipulating the DOM structure in a pythonic way.
Author-email: Jakob Axelsson <jakob.pm.axelsson@gmail.com>
Classifier: License :: OSI Approved :: MIT License
Project-URL: Home, https://github.com/jakobaxelsson/domed
